toolbox_parallel_robots/__init__.py
toolbox_parallel_robots/actuation.py
toolbox_parallel_robots/actuation_data.py
toolbox_parallel_robots/actuation_model.py
toolbox_parallel_robots/closures.py
toolbox_parallel_robots/constraints.py
toolbox_parallel_robots/forward_kinematics.py
toolbox_parallel_robots/freeze_joints.py
toolbox_parallel_robots/inverse_dynamics.py
toolbox_parallel_robots/inverse_kinematics.py
toolbox_parallel_robots/jacobian.py
toolbox_parallel_robots/mounting.py
toolbox_parallel_robots/projections.py
toolbox_parallel_robots/sliders/foo.py
toolbox_parallel_robots/sliders/tk_robot_sliders.py
toolbox_parallel_robots/sliders/tk_sliders_manager.py
toolbox_parallel_robots/sliders/util_frames.py
toolbox_parallel_robots-1.2.0.dist-info/WHEEL
toolbox_parallel_robots-1.2.0.dist-info/METADATA
toolbox_parallel_robots-1.2.0.dist-info/RECORD
