Metadata-Version: 2.3
Name: toolbox-parallel-robots
Version: 1.2.0
Summary: Add your description here
Author: Virgile Batto, Ludovic De Matteis
Author-email: Virgile Batto <vbatto@laas.fr>, Ludovic De Matteis <ldematteis@laas.fr>
Requires-Dist: pin>=3.7.0
Maintainer: Guilhem Saurel
Maintainer-email: Guilhem Saurel <guilhem.saurel@laas.fr>
Requires-Python: >=3.8
